cicc_excel/__init__.py
cicc_excel/excelwriter.py
cicc_excel-0.4.1.dist-info/LICENSE
cicc_excel-0.4.1.dist-info/METADATA
cicc_excel-0.4.1.dist-info/WHEEL
cicc_excel-0.4.1.dist-info/top_level.txt
cicc_excel-0.4.1.dist-info/RECORD
