Metadata-Version: 2.1
Name: cicc_excel
Version: 0.4.1
Summary: Library of export pandas into excel for CICCers
Home-page: https://github.com/nyuspc/cicc_excel
Author: Pengcheng Song
Author-email: smth_spc@hotmail.com
Classifier: Programming Language :: Python
Classifier: Intended Audience :: Financial and Insurance Industry
Classifier: Topic :: Scientific/Engineering :: Mathematics
Classifier: License :: OSI Approved :: MIT License
Classifier: Operating System :: OS Independent
License-File: LICENSE
Requires-Dist: pandas
Requires-Dist: xlsxwriter
